mofapy2/__init__.py
mofapy2/build_model/__init__.py
mofapy2/build_model/build_model.py
mofapy2/build_model/init_model.py
mofapy2/build_model/save_model.py
mofapy2/build_model/train_model.py
mofapy2/build_model/utils.py
mofapy2/config.py
mofapy2/core/BayesNet.py
mofapy2/core/__init__.py
mofapy2/core/distributions/__init__.py
mofapy2/core/distributions/basic_distributions.py
mofapy2/core/distributions/bernoulli.py
mofapy2/core/distributions/bernoulli_gaussian.py
mofapy2/core/distributions/beta.py
mofapy2/core/distributions/binomial.py
mofapy2/core/distributions/gamma.py
mofapy2/core/distributions/multi_task_GP.py
mofapy2/core/distributions/multivariate_gaussian.py
mofapy2/core/distributions/poisson.py
mofapy2/core/distributions/univariate_gaussian.py
mofapy2/core/gp_utils.py
mofapy2/core/gpu_utils.py
mofapy2/core/nodes/Alpha_nodes.py
mofapy2/core/nodes/Kc_node.py
mofapy2/core/nodes/Kg_node.py
mofapy2/core/nodes/Sigma_node.py
mofapy2/core/nodes/Tau_nodes.py
mofapy2/core/nodes/Theta_nodes.py
mofapy2/core/nodes/U_nodes.py
mofapy2/core/nodes/W_nodes.py
mofapy2/core/nodes/Y_nodes.py
mofapy2/core/nodes/Z_nodes.py
mofapy2/core/nodes/Z_nodes_GP.py
mofapy2/core/nodes/Z_nodes_GP_mv.py
mofapy2/core/nodes/ZgU_node.py
mofapy2/core/nodes/__init__.py
mofapy2/core/nodes/basic_nodes.py
mofapy2/core/nodes/multiview_nodes.py
mofapy2/core/nodes/nongaussian_nodes.py
mofapy2/core/nodes/variational_nodes.py
mofapy2/core/utils.py
mofapy2/notebooks/getting_started_python.ipynb
mofapy2/notebooks/run_mofa_cpu_vs_gpu.py
mofapy2/notebooks/test_cupy.py
mofapy2/run/__init__.py
mofapy2/run/entry_point.py
mofapy2/run/test_data/view_0.txt
mofapy2/run/test_data/view_1.txt
mofapy2/run/test_data/view_2.txt
mofapy2/run/test_data/with_nas/500_0.txt
mofapy2/run/test_data/with_nas/500_1.txt
mofapy2/run/test_data/with_nas/500_2.txt
mofapy2/simulate/__init__.py
mofapy2/simulate/simulate_mofa.py
mofapy2/version.py
mofapy2-0.7.3.dist-info/METADATA
mofapy2-0.7.3.dist-info/WHEEL
mofapy2-0.7.3.dist-info/licenses/LICENSE
mofapy2-0.7.3.dist-info/RECORD
