Metadata-Version: 2.4
Name: mofapy2
Version: 0.7.3
Summary: Multi-omics factor analysis
License: LGPL-3.0
License-File: LICENSE
Author: Ricard Argelaguet
Requires-Python: >=3.8,<4.0
Classifier: License :: OSI Approved :: GNU Lesser General Public License v3 (LGPLv3)
Classifier: Programming Language :: Python :: 3
Classifier: Programming Language :: Python :: 3.8
Classifier: Programming Language :: Python :: 3.9
Classifier: Programming Language :: Python :: 3.10
Classifier: Programming Language :: Python :: 3.11
Classifier: Programming Language :: Python :: 3.12
Classifier: Programming Language :: Python :: 3.13
Classifier: Programming Language :: Python :: 3.14
Requires-Dist: h5py (>=3,<4)
Requires-Dist: numpy
Requires-Dist: pandas
Requires-Dist: scikit-learn (>=1,<2)
Requires-Dist: scipy (>=1,<2)
Project-URL: Homepage, https:/biofam.github.io/MOFA2/
Project-URL: Repository, https://github.com/bioFAM/mofapy2
